{
  "pagesScanned": 335,
  "uniqueNavLinks": 73,
  "brokenNavLinks": 0,
  "links": [
    {
      "href": "/website-v3/case-studies/",
      "pages": 326,
      "status": "ok",
      "target": "case-studies/index.html"
    },
    {
      "href": "/website-v3/contact-us",
      "pages": 326,
      "status": "ok",
      "target": "contact-us/index.html"
    },
    {
      "href": "/website-v3/features/corporate-client-portal/",
      "pages": 326,
      "status": "ok",
      "target": "features/corporate-client-portal/index.html"
    },
    {
      "href": "/website-v3/features/transformation-project-progress-dashboard/",
      "pages": 326,
      "status": "ok",
      "target": "features/transformation-project-progress-dashboard/index.html"
    },
    {
      "href": "/website-v3/features/xiri-analytics/",
      "pages": 326,
      "status": "ok",
      "target": "features/xiri-analytics/index.html"
    },
    {
      "href": "/website-v3/getit-nominate/",
      "pages": 326,
      "status": "ok",
      "target": "getit-nominate/index.html"
    },
    {
      "href": "/website-v3/insights",
      "pages": 326,
      "status": "ok",
      "target": "insights/index.html"
    },
    {
      "href": "/website-v3/insights/",
      "pages": 326,
      "status": "ok",
      "target": "insights/index.html"
    },
    {
      "href": "/website-v3/insights/xiripedia/",
      "pages": 326,
      "status": "ok",
      "target": "insights/xiripedia/index.html"
    },
    {
      "href": "/website-v3/insights/xiripedia/submission-form/",
      "pages": 326,
      "status": "ok",
      "target": "insights/xiripedia/submission-form/index.html"
    },
    {
      "href": "/website-v3/newsletter",
      "pages": 326,
      "status": "ok",
      "target": "newsletter/index.html"
    },
    {
      "href": "/website-v3/newsletter/",
      "pages": 326,
      "status": "ok",
      "target": "newsletter/index.html"
    },
    {
      "href": "/website-v3/newsroom",
      "pages": 326,
      "status": "ok",
      "target": "newsroom/index.html"
    },
    {
      "href": "/website-v3/newsroom/",
      "pages": 326,
      "status": "ok",
      "target": "newsroom/index.html"
    },
    {
      "href": "/website-v3/prioritise-plus-marketplace/",
      "pages": 326,
      "status": "ok",
      "target": "prioritise-plus-marketplace/index.html"
    },
    {
      "href": "/website-v3/prioritise-plus-marketplace/assessors/",
      "pages": 326,
      "status": "ok",
      "target": "prioritise-plus-marketplace/assessors/index.html"
    },
    {
      "href": "/website-v3/prioritise-plus-marketplace/clients/",
      "pages": 326,
      "status": "ok",
      "target": "prioritise-plus-marketplace/clients/index.html"
    },
    {
      "href": "/website-v3/prioritise-plus-marketplace/providers/",
      "pages": 326,
      "status": "ok",
      "target": "prioritise-plus-marketplace/providers/index.html"
    },
    {
      "href": "/website-v3/privacy-policy",
      "pages": 326,
      "status": "ok",
      "target": "privacy-policy/index.html"
    },
    {
      "href": "/website-v3/sitemap",
      "pages": 326,
      "status": "ok",
      "target": "sitemap/index.html"
    },
    {
      "href": "/website-v3/terms-of-use",
      "pages": 326,
      "status": "ok",
      "target": "terms-of-use/index.html"
    },
    {
      "href": "/website-v3/thought-leadership/",
      "pages": 326,
      "status": "ok",
      "target": "thought-leadership/index.html"
    },
    {
      "href": "/website-v3/training-and-certification/",
      "pages": 326,
      "status": "ok",
      "target": "training-and-certification/index.html"
    },
    {
      "href": "/website-v3/training-and-certification/all-courses/",
      "pages": 326,
      "status": "ok",
      "target": "training-and-certification/all-courses/index.html"
    },
    {
      "href": "/website-v3/training-and-certification/contact-list/",
      "pages": 326,
      "status": "ok",
      "target": "training-and-certification/contact-list/index.html"
    },
    {
      "href": "/website-v3/verify/",
      "pages": 326,
      "status": "ok",
      "target": "verify/index.html"
    },
    {
      "href": "/website-v3/verify/file/",
      "pages": 326,
      "status": "ok",
      "target": "verify/file/index.html"
    },
    {
      "href": "/website-v3/verify/scan-qr/",
      "pages": 326,
      "status": "ok",
      "target": "verify/scan-qr/index.html"
    },
    {
      "href": "/website-v3/what-we-do",
      "pages": 326,
      "status": "ok",
      "target": "what-we-do/index.html"
    },
    {
      "href": "/website-v3/what-we-do/aimri/",
      "pages": 326,
      "status": "ok",
      "target": "what-we-do/aimri/index.html"
    },
    {
      "href": "/website-v3/what-we-do/aimri/assessment/",
      "pages": 326,
      "status": "ok",
      "target": "what-we-do/aimri/assessment/index.html"
    },
    {
      "href": "/website-v3/what-we-do/aimri/become-certified-aimri-assessor/",
      "pages": 326,
      "status": "ok",
      "target": "what-we-do/aimri/become-certified-aimri-assessor/index.html"
    },
    {
      "href": "/website-v3/what-we-do/aimri/become-training-and-certification-partner/",
      "pages": 326,
      "status": "ok",
      "target": "what-we-do/aimri/become-training-and-certification-partner/index.html"
    },
    {
      "href": "/website-v3/what-we-do/aimri/certified-assessor/",
      "pages": 326,
      "status": "ok",
      "target": "what-we-do/aimri/certified-assessor/index.html"
    },
    {
      "href": "/website-v3/what-we-do/aimri/framework/",
      "pages": 326,
      "status": "ok",
      "target": "what-we-do/aimri/framework/index.html"
    },
    {
      "href": "/website-v3/what-we-do/cosiri/",
      "pages": 326,
      "status": "ok",
      "target": "what-we-do/cosiri/index.html"
    },
    {
      "href": "/website-v3/what-we-do/cosiri/cosiri-10/",
      "pages": 326,
      "status": "ok",
      "target": "what-we-do/cosiri/cosiri-10/index.html"
    },
    {
      "href": "/website-v3/what-we-do/cosiri/cosiri-24/",
      "pages": 326,
      "status": "ok",
      "target": "what-we-do/cosiri/cosiri-24/index.html"
    },
    {
      "href": "/website-v3/what-we-do/cosiri/cosiri-assessment/",
      "pages": 326,
      "status": "ok",
      "target": "what-we-do/cosiri/cosiri-assessment/index.html"
    },
    {
      "href": "/website-v3/what-we-do/cosiri/cosiri-training/",
      "pages": 326,
      "status": "ok",
      "target": "what-we-do/cosiri/cosiri-training/index.html"
    },
    {
      "href": "/website-v3/what-we-do/cosiri/esg-data-analytics/",
      "pages": 326,
      "status": "ok",
      "target": "what-we-do/cosiri/esg-data-analytics/index.html"
    },
    {
      "href": "/website-v3/what-we-do/cosiri/key-differences/",
      "pages": 326,
      "status": "ok",
      "target": "what-we-do/cosiri/key-differences/index.html"
    },
    {
      "href": "/website-v3/what-we-do/cosiri/request-assessment/",
      "pages": 326,
      "status": "ok",
      "target": "what-we-do/cosiri/request-assessment/index.html"
    },
    {
      "href": "/website-v3/what-we-do/getit/",
      "pages": 326,
      "status": "ok",
      "target": "what-we-do/getit/index.html"
    },
    {
      "href": "/website-v3/what-we-do/manuvate/",
      "pages": 326,
      "status": "ok",
      "target": "what-we-do/manuvate/index.html"
    },
    {
      "href": "/website-v3/what-we-do/operi/",
      "pages": 326,
      "status": "ok",
      "target": "what-we-do/operi/index.html"
    },
    {
      "href": "/website-v3/what-we-do/operi/consultants/",
      "pages": 326,
      "status": "ok",
      "target": "what-we-do/operi/consultants/index.html"
    },
    {
      "href": "/website-v3/what-we-do/operi/governments-trade-associations",
      "pages": 326,
      "status": "ok",
      "target": "what-we-do/operi/governments-trade-associations/index.html"
    },
    {
      "href": "/website-v3/what-we-do/operi/governments-trade-associations/",
      "pages": 326,
      "status": "ok",
      "target": "what-we-do/operi/governments-trade-associations/index.html"
    },
    {
      "href": "/website-v3/what-we-do/operi/how-to-use-app/",
      "pages": 326,
      "status": "ok",
      "target": "what-we-do/operi/how-to-use-app/index.html"
    },
    {
      "href": "/website-v3/what-we-do/operi/small-businesses/",
      "pages": 326,
      "status": "ok",
      "target": "what-we-do/operi/small-businesses/index.html"
    },
    {
      "href": "/website-v3/what-we-do/operi/training-certification-centres/",
      "pages": 326,
      "status": "ok",
      "target": "what-we-do/operi/training-certification-centres/index.html"
    },
    {
      "href": "/website-v3/what-we-do/siri/",
      "pages": 326,
      "status": "ok",
      "target": "what-we-do/siri/index.html"
    },
    {
      "href": "/website-v3/what-we-do/siri/assessment/",
      "pages": 326,
      "status": "ok",
      "target": "what-we-do/siri/assessment/index.html"
    },
    {
      "href": "/website-v3/what-we-do/siri/become-training-certification-partner/",
      "pages": 326,
      "status": "ok",
      "target": "what-we-do/siri/become-training-certification-partner/index.html"
    },
    {
      "href": "/website-v3/what-we-do/siri/certified-assessor/",
      "pages": 326,
      "status": "ok",
      "target": "what-we-do/siri/certified-assessor/index.html"
    },
    {
      "href": "/website-v3/what-we-do/siri/programme/",
      "pages": 326,
      "status": "ok",
      "target": "what-we-do/siri/programme/index.html"
    },
    {
      "href": "/website-v3/who-we-are",
      "pages": 326,
      "status": "ok",
      "target": "who-we-are/index.html"
    },
    {
      "href": "/website-v3/who-we-are/",
      "pages": 326,
      "status": "ok",
      "target": "who-we-are/index.html"
    },
    {
      "href": "/website-v3/who-we-are/advisory-board/",
      "pages": 326,
      "status": "ok",
      "target": "who-we-are/advisory-board/index.html"
    },
    {
      "href": "/website-v3/who-we-are/partner-network/",
      "pages": 326,
      "status": "ok",
      "target": "who-we-are/partner-network/index.html"
    },
    {
      "href": "/website-v3/who-we-are/regional-ambassadors/",
      "pages": 326,
      "status": "ok",
      "target": "who-we-are/regional-ambassadors/index.html"
    },
    {
      "href": "/website-v3/who-we-support/academic-institutions-certification-bodies/",
      "pages": 326,
      "status": "ok",
      "target": "who-we-support/academic-institutions-certification-bodies/index.html"
    },
    {
      "href": "/website-v3/who-we-support/consultants/",
      "pages": 326,
      "status": "ok",
      "target": "who-we-support/consultants/index.html"
    },
    {
      "href": "/website-v3/who-we-support/equity-firms/",
      "pages": 326,
      "status": "ok",
      "target": "who-we-support/equity-firms/index.html"
    },
    {
      "href": "/website-v3/who-we-support/government-trade-associations/",
      "pages": 326,
      "status": "ok",
      "target": "who-we-support/government-trade-associations/index.html"
    },
    {
      "href": "/website-v3/who-we-support/industrial-start-ups/",
      "pages": 326,
      "status": "ok",
      "target": "who-we-support/industrial-start-ups/index.html"
    },
    {
      "href": "/website-v3/who-we-support/manufacturers/",
      "pages": 326,
      "status": "ok",
      "target": "who-we-support/manufacturers/index.html"
    },
    {
      "href": "/website-v3/who-we-support/technology-solution-providers/",
      "pages": 326,
      "status": "ok",
      "target": "who-we-support/technology-solution-providers/index.html"
    },
    {
      "href": "https://cosiri.incit.org",
      "pages": 326,
      "status": "external",
      "target": "https://cosiri.incit.org"
    },
    {
      "href": "https://operi.incit.org/download-app",
      "pages": 326,
      "status": "external",
      "target": "https://operi.incit.org/download-app"
    },
    {
      "href": "https://readiness.incit.org",
      "pages": 326,
      "status": "external",
      "target": "https://readiness.incit.org"
    },
    {
      "href": "https://siri.incit.org",
      "pages": 326,
      "status": "external",
      "target": "https://siri.incit.org"
    }
  ],
  "brokenDetails": []
}
